scalib-0.6.4.dist-info/RECORD
scalib-0.6.4.dist-info/WHEEL
scalib-0.6.4.dist-info/top_level.txt
scalib-0.6.4.dist-info/METADATA
scalib-0.6.4.dist-info/licenses/COPYING
scalib/version.py
scalib/tools.py
scalib/__init__.py
scalib/_cpu_check.abi3.so
scalib/utils.py
scalib/_scalib_ext.abi3.so
scalib/build_config.py
scalib/metrics/information.py
scalib/metrics/ttest.py
scalib/metrics/__init__.py
scalib/metrics/snr.py
scalib/config/__init__.py
scalib/config/threading.py
scalib/modeling/rldaclassifier.py
scalib/modeling/lda.py
scalib/modeling/__init__.py
scalib/postprocessing/rankestimation.py
scalib/postprocessing/__init__.py
scalib/preprocessing/quantization.py
scalib/preprocessing/__init__.py
scalib/attacks/factor_graph.py
scalib/attacks/__init__.py
scalib/attacks/cpa.py
