Metadata-Version: 2.4
Name: scalib
Version: 0.6.4
Summary: Side-Channel Analysis Library
Author-email: SCALib contributors <info@simple-crypto.org>
Maintainer-email: Gaëtan Cassiers <gaetan.cassiers@uclouvain.be>
License: GNU AGPL 3.0
Project-URL: Homepage, https://github.com/simple-crypto/SCALib
Project-URL: Documentation, https://https://scalib.readthedocs.io/
Project-URL: Repository, https://github.com/simple-crypto/SCALib.git
Project-URL: Issues, https://github.com/simple-crypto/SCALib/issues
Project-URL: Changelog, https://github.com/simple-crypto/SCALib/blob/main/CHANGELOG.rst
Requires-Python: >=3.10
License-File: COPYING
Requires-Dist: numpy<3,>=1.26.0
Dynamic: license-file
